{
   "0": "distance 1_miles traffic_info no_traffic poi_type shopping_center address 338_alester_ave poi midtown_shopping_center",
   "1": "distance 6_miles traffic_info heavy_traffic poi_type friends_house address 580_van_ness_ave poi toms_house",
   "2": "distance 3_miles traffic_info car_collision_nearby poi_type coffee_or_tea_place address 269_alger_dr poi cafe_venetia",
   "3": "distance 6_miles traffic_info moderate_traffic poi_type rest_stop address 329_el_camino_real poi the_westin",
   "4": "distance 1_miles traffic_info road_block_nearby poi_type grocery_store address 1313_chester_ave poi hacienda_market",
   "5": "distance 1_miles traffic_info no_traffic poi_type hospital address 611_ames_ave poi palo_alto_medical_foundation",
   "6": "distance 3_miles traffic_info car_collision_nearby poi_type parking_garage address 880_ames_ct poi webster_garage",
   "7": "distance 5_miles traffic_info heavy_traffic poi_type chinese_restaurant address 669_el_camino_real poi p_._f_._changs"
}