{
   "0": "distance 2_miles traffic_info moderate_traffic poi_type grocery_store address 638_amherst_st poi sigona_farmers_market",
   "1": "distance 3_miles traffic_info no_traffic poi_type shopping_center address 434_arastradero_rd poi ravenswood_shopping_center",
   "2": "distance 2_miles traffic_info no_traffic poi_type certain_address address 5672_barringer_street poi 5672_barringer_street",
   "3": "distance 2_miles traffic_info heavy_traffic poi_type parking_garage address 481_amaranta_ave poi palo_alto_garage_r",
   "4": "distance 4_miles traffic_info moderate_traffic poi_type hospital address 899_ames_ct poi stanford_childrens_health",
   "5": "distance 3_miles traffic_info heavy_traffic poi_type friends_house address 580_van_ness_ave poi toms_house",
   "6": "distance 6_miles traffic_info no_traffic poi_type gas_station address 783_arcadia_pl poi chevron"
}